onchebot/__init__.py
onchebot/api.py
onchebot/bot.py
onchebot/bot_module.py
onchebot/command.py
onchebot/conftest.py
onchebot/consumer.py
onchebot/db.py
onchebot/dictionnaries.py
onchebot/globals.py
onchebot/metrics.py
onchebot/models.py
onchebot/onche.py
onchebot/producer.py
onchebot/scraper.py
onchebot/task.py
onchebot/test.py
onchebot/examples/__init__.py
onchebot/examples/apod.py
onchebot/examples/counter.py
onchebot/examples/hangman.py
onchebot/examples/pingpong.py
onchebot/examples/repeater.py
onchebot/modules/__init__.py
onchebot/modules/misc.py
onchebot/modules/vote.py
onchebot/tests/counter.py
onchebot/tests/hangman.py
onchebot/tests/misc.py
onchebot/tests/pingpong.py
onchebot-0.2.1.dist-info/licenses/LICENSE
onchebot-0.2.1.dist-info/METADATA
onchebot-0.2.1.dist-info/WHEEL
onchebot-0.2.1.dist-info/top_level.txt
onchebot-0.2.1.dist-info/RECORD
