Metadata-Version: 2.4
Name: onchebot
Version: 0.2.1
Author-email: Pepe <pepe-onche@proton.me>
Project-URL: Homepage, https://github.com/pepe-onche/onchebot
Classifier: Programming Language :: Python
Classifier: Programming Language :: Python :: 3
Requires-Python: >=3.11
License-File: LICENSE
Requires-Dist: aiohttp==3.9.3
Requires-Dist: aiolimiter==1.1.0
Requires-Dist: async_timeout==5.0.1
Requires-Dist: beautifulsoup4==4.12.3
Requires-Dist: dacite==1.8.1
Requires-Dist: pytest==7.4.4
Requires-Dist: pytest-mock==3.14.0
Requires-Dist: pytest-asyncio==0.23.6
Requires-Dist: googletrans==4.0.2
Requires-Dist: apscheduler==3.11.0
Requires-Dist: python-logging-loki==0.3.1
Requires-Dist: prometheus-client==0.21.0
Requires-Dist: tortoise-orm==0.24.0
Dynamic: license-file
